[{"_id":"62622faad4c6e5a0cbc2afd9","name":"Fridge","section":"Kitchen","imgURL":"http://live.staticflickr.com/2224/2471862881_4db94432b8_n.jpg","person":"João","status":"checked"},{"_id":"62622faad4c6e5a0cbc2afda","name":"Cooktop","section":"Kitchen","imgURL":"http://live.staticflickr.com/5461/7230797092_5fb5bfa6d4_n.jpg","person":"João","status":"checked"},{"_id":"62622faad4c6e5a0cbc2afdb","name":"Washing machine","section":"Outside","imgURL":"http://live.staticflickr.com/886/41394816255_bab13dd3c0_n.jpg","person":"Undefined","status":""},{"_id":"62622faad4c6e5a0cbc2afdc","name":"Glass brown mugs","section":"Kitchen","imgURL":"http://live.staticflickr.com/4694/39117121804_c45d3b9d66_n.jpg","person":"Mateus","status":"checked"},{"_id":"62622faad4c6e5a0cbc2afdd","name":"Soap bar","section":"Toilet","imgURL":"http://live.staticflickr.com/65535/50888491362_fee6216f46_n.jpg","person":"Undefined","status":""},{"_id":"62622faad4c6e5a0cbc2afde","name":"Frying pan","section":"Kitchen","imgURL":"http://live.staticflickr.com/2290/3620205347_82fe8578f9_n.jpg","person":"Undefined","status":""},{"_id":"62622faad4c6e5a0cbc2afdf","name":"Pressure cooker","section":"Kitchen","imgURL":"http://live.staticflickr.com/8671/16464219688_8030c79b0d_n.jpg","person":"Undefined","status":""},{"_id":"62622faad4c6e5a0cbc2afe0","name":"Detergent bottle","section":"Kitchen","imgURL":"http://live.staticflickr.com/8210/8243486799_85423218cf_n.jpg","person":"Undefined","status":""},{"_id":"62622faad4c6e5a0cbc2afe1","name":"Floor squeegee","section":"Outside","imgURL":"http://live.staticflickr.com/63/199235925_981c1da1c7_n.jpg","person":"Undefined","status":""},{"_id":"62622faad4c6e5a0cbc2afe2","name":"Cleaning cloth","section":"Outside","imgURL":"http://live.staticflickr.com/65535/49730535013_fd31f5629b_n.jpg","person":"Undefined","status":""},{"_id":"62622faad4c6e5a0cbc2afe3","name":"Cleaning bucket","section":"Outside","imgURL":"http://live.staticflickr.com/7297/27582231804_40306281d0_n.jpg","person":"Undefined","status":""},{"_id":"62622faad4c6e5a0cbc2afe4","name":"Glass plates","section":"Kitchen","imgURL":"http://live.staticflickr.com/3344/5788294465_01035264aa_n.jpg","person":"Undefined","status":""},{"_id":"62622faad4c6e5a0cbc2afe5","name":"Spatula","section":"Kitchen","imgURL":"http://live.staticflickr.com/2069/2247239211_c247445d8b_n.jpg","person":"Undefined","status":""},{"_id":"62622faad4c6e5a0cbc2afe6","name":"Skimmer spoon","section":"Kitchen","imgURL":"http://live.staticflickr.com/7643/17147187575_727cf7e419_n.jpg","person":"Undefined","status":""},{"_id":"62622faad4c6e5a0cbc2afe7","name":"Electric kettle","section":"Kitchen","imgURL":"http://live.staticflickr.com/65535/51244229517_b29b108022_n.jpg","person":"Mateus","status":"checked"},{"_id":"62622faad4c6e5a0cbc2afe8","name":"Coffee vacuum flask","section":"Kitchen","imgURL":"http://live.staticflickr.com/65535/51809287627_85170cede5_n.jpg","person":"João","status":"checked"},{"_id":"62622faad4c6e5a0cbc2afe9","name":"Stainless steel coffee pot","section":"Kitchen","imgURL":"http://live.staticflickr.com/695/20666207654_212d6de685_n.jpg","person":"Mateus","status":"checked"},{"_id":"62622faad4c6e5a0cbc2afea","name":"Coffee filter","section":"Kitchen","imgURL":"http://live.staticflickr.com/65535/49919755161_aacf59ca8e_n.jpg","person":"Mateus","status":"checked"},{"_id":"62622faad4c6e5a0cbc2afeb","name":"Kitchen storage containers","section":"Kitchen","imgURL":"https://live.staticflickr.com/7228/7217883804_5f0f18c4a6_n.jpg","person":"Mateus","status":"checked"},{"_id":"62622faad4c6e5a0cbc2afec","name":"Cutlery drawer","section":"Kitchen","imgURL":"http://live.staticflickr.com/8694/16369456143_a23b531cb9_n.jpg","person":"Undefined","status":""},{"_id":"62622faad4c6e5a0cbc2afed","name":"Kitchen scissors","section":"Kitchen","imgURL":"http://live.staticflickr.com/7481/27113039022_5e8c97146f_n.jpg","person":"Mateus","status":"checked"},{"_id":"62622faad4c6e5a0cbc2afee","name":"Microwave","section":"Kitchen","imgURL":"http://live.staticflickr.com/124/392968772_0b33032012_n.jpg","person":"Undefined","status":""},{"_id":"62622faad4c6e5a0cbc2afef","name":"Kitchen trash can","section":"Kitchen","imgURL":"http://live.staticflickr.com/7840/40099295593_81e57af2b4_n.jpg","person":"João","status":"checked"},{"_id":"62622faad4c6e5a0cbc2aff0","name":"Cutlery","section":"Kitchen","imgURL":"http://live.staticflickr.com/1201/5128962543_f7b913ac8c_n.jpg","person":"Undefined","status":""},{"_id":"62622faad4c6e5a0cbc2aff1","name":"Toilet brush","section":"Toilet","imgURL":"http://live.staticflickr.com/739/21372116141_b43140500f_n.jpg","person":"Mateus","status":"checked"},{"_id":"62622faad4c6e5a0cbc2aff2","name":"Kitchen knife","section":"Kitchen","imgURL":"http://live.staticflickr.com/4154/4993917610_63d1d1b714_n.jpg","person":"Undefined","status":""},{"_id":"62622faad4c6e5a0cbc2aff3","name":"Plastic fruit basket","section":"Kitchen","imgURL":"http://live.staticflickr.com/43/110567437_c43f6feea5_n.jpg","person":"Undefined","status":""},{"_id":"62622faad4c6e5a0cbc2aff4","name":"Sharpening steel","section":"Kitchen","imgURL":"http://live.staticflickr.com/8337/8254995969_004454a532_n.jpg","person":"Undefined","status":""},{"_id":"62622faad4c6e5a0cbc2aff5","name":"Slotted spoon","section":"Kitchen","imgURL":"http://live.staticflickr.com/2101/1984604709_f41838fe5c_n.jpg","person":"Undefined","status":""},{"_id":"62622faad4c6e5a0cbc2aff6","name":"Plastic pitcher","section":"Kitchen","imgURL":"https://live.staticflickr.com/7098/7114294953_1de69e5d7e_n.jpg","person":"Mateus","status":"checked"},{"_id":"62622faad4c6e5a0cbc2aff7","name":"Glass cups","section":"Kitchen","imgURL":"http://live.staticflickr.com/7132/7444415430_9e71a19cbe_n.jpg","person":"Undefined","status":""},{"_id":"62622faad4c6e5a0cbc2aff8","name":"Garlic chopper","section":"Kitchen","imgURL":"http://live.staticflickr.com/65535/51983581888_6eb10b6de7_n.jpg","person":"Mateus","status":"checked"},{"_id":"62622faad4c6e5a0cbc2aff9","name":"Grater","section":"Kitchen","imgURL":"http://live.staticflickr.com/65535/49961090408_fb09cb4e19_n.jpg","person":"João","status":"checked"},{"_id":"62622faad4c6e5a0cbc2affa","name":"Sandwich toaster","section":"Kitchen","imgURL":"https://live.staticflickr.com/8579/16273655812_a2d44c1114_n.jpg","person":"João","status":"checked"},{"_id":"62622faad4c6e5a0cbc2affb","name":"Air fryer","section":"Kitchen","imgURL":"https://live.staticflickr.com/65535/51742414927_0aaeb042c9_n.jpg","person":"Mateus","status":"checked"},{"_id":"62622faad4c6e5a0cbc2affc","name":"Mixer and crushing machine","section":"Kitchen","imgURL":"https://live.staticflickr.com/3588/3352391750_956197a87b_n.jpg","person":"João","status":"checked"},{"_id":"62622faad4c6e5a0cbc2affd","name":"Blender","section":"Kitchen","imgURL":"http://live.staticflickr.com/65535/50995689163_089ebec0dd_n.jpg","person":"Mateus","status":"checked"},{"_id":"62622faad4c6e5a0cbc2afff","name":"Cabinet","section":"Kitchen","imgURL":"http://live.staticflickr.com/4004/4320355273_07d0d9044b_n.jpg","person":"Mateus","status":"checked"},{"_id":"62622faad4c6e5a0cbc2b000","name":"Plastic liquid soap dispenser","section":"Toilet","imgURL":"http://live.staticflickr.com/65535/49741802722_47c3294e8b_n.jpg","person":"Undefined","status":""},{"_id":"62622faad4c6e5a0cbc2b001","name":"Dishwashing sponge","section":"Kitchen","imgURL":"https://live.staticflickr.com/65535/49700318127_f01cb4b28a_n.jpg","person":"Mateus","status":"checked"},{"_id":"62622faad4c6e5a0cbc2b002","name":"Sponge and detergent holder","section":"Kitchen","imgURL":"https://live.staticflickr.com/5445/17357729188_63dda1ddf5_n.jpg","person":"Mateus","status":"checked"},{"_id":"62622faad4c6e5a0cbc2b003","name":"Toothbrush holder","section":"Toilet","imgURL":"https://live.staticflickr.com/7021/6419730167_7804c8ba41_n.jpg","person":"Mateus","status":"checked"},{"_id":"62622faad4c6e5a0cbc2b004","name":"Another kitchen cabinet","section":"Kitchen","imgURL":"http://live.staticflickr.com/6100/6372479639_cdc92afb34_n.jpg","person":"Undefined","status":""},{"_id":"62622faad4c6e5a0cbc2b005","name":"Cutting board","section":"Kitchen","imgURL":"http://live.staticflickr.com/8376/8519390684_271e70ae8a_n.jpg","person":"Mateus","status":"checked"},{"_id":"62622faad4c6e5a0cbc2b006","name":"Beans","section":"Food","imgURL":"http://live.staticflickr.com/4005/4300636744_3dcb938a25_n.jpg","person":"Undefined","status":""},{"_id":"62622faad4c6e5a0cbc2b008","name":"Salt shaker","section":"Kitchen","imgURL":"http://live.staticflickr.com/156/428432872_c2c8ebaf06_n.jpg","person":"João","status":"checked"},{"_id":"62622faad4c6e5a0cbc2b009","name":"Measuring cup","section":"Kitchen","imgURL":"https://live.staticflickr.com/4092/5146230716_78374414f0_n.jpg","person":"Undefined","status":""},{"_id":"62622faad4c6e5a0cbc2b00a","name":"Cutlery drying rack","section":"Kitchen","imgURL":"https://live.staticflickr.com/65535/50783999806_287c7478d2_n.jpg","person":"Undefined","status":""},{"_id":"62622faad4c6e5a0cbc2b00b","name":"Colander","section":"Kitchen","imgURL":"https://live.staticflickr.com/65535/51244856679_928281fd97_n.jpg","person":"Undefined","status":""},{"_id":"62622faad4c6e5a0cbc2b00c","name":"Dish rack","section":"Kitchen","imgURL":"https://live.staticflickr.com/4160/33438690014_62217310cd_n.jpg","person":"Undefined","status":""},{"_id":"62622faad4c6e5a0cbc2b00d","name":"Canister","section":"Kitchen","imgURL":"https://live.staticflickr.com/3327/3342076889_b4630bc8cf_n.jpg","person":"Undefined","status":""},{"_id":"62622faad4c6e5a0cbc2b00e","name":"Spices container","section":"Kitchen","imgURL":"https://live.staticflickr.com/65535/50070980023_915f6d5a72_n.jpg","person":"Undefined","status":""},{"_id":"62622faad4c6e5a0cbc2b00f","name":"Toilet towel","section":"Toilet","imgURL":"http://live.staticflickr.com/1423/1325892020_8ef9b5ceb0_n.jpg","person":"Undefined","status":""},{"_id":"62622faad4c6e5a0cbc2b010","name":"Toilet papper","section":"Toilet","imgURL":"https://live.staticflickr.com/53/149286218_1cf1c736a3_n.jpg","person":"Undefined","status":""},{"_id":"62622faad4c6e5a0cbc2b011","name":"Toothpaste","section":"Toilet","imgURL":"http://live.staticflickr.com/3317/3305804969_2e291a0197_n.jpg","person":"Undefined","status":""},{"_id":"62622faad4c6e5a0cbc2b012","name":"Trash can","section":"Outside","imgURL":"https://live.staticflickr.com/4032/4457572969_0bac693204_n.jpg","person":"Undefined","status":""},{"_id":"62622faad4c6e5a0cbc2b013","name":"Trash can","section":"Toilet","imgURL":"https://live.staticflickr.com/3757/9622075620_0afe19ca2e_n.jpg","person":"Undefined","status":""},{"_id":"62622faad4c6e5a0cbc2b014","name":"Sink trash can","section":"Kitchen","imgURL":"https://live.staticflickr.com/65535/51405421111_b9f86c66ca_n.jpg","person":"Undefined","status":""},{"_id":"62622faad4c6e5a0cbc2b015","name":"Light bulb","section":"Kitchen","imgURL":"http://live.staticflickr.com/5291/5475547537_3bfd60961f_n.jpg","person":"Undefined","status":""},{"_id":"62622faad4c6e5a0cbc2b016","name":"Light bulb","section":"Toilet","imgURL":"http://live.staticflickr.com/5291/5475547537_3bfd60961f_n.jpg","person":"Undefined","status":""},{"_id":"62622faad4c6e5a0cbc2b017","name":"Shower head","section":"Toilet","imgURL":"https://live.staticflickr.com/7106/7817968350_f56c15aa9b_n.jpg","person":"Undefined","status":""},{"_id":"62622faad4c6e5a0cbc2b018","name":"Floor mat","section":"Outside","imgURL":"https://live.staticflickr.com/65535/49121091177_87acf0085e_n.jpg","person":"Undefined","status":""},{"_id":"62622faad4c6e5a0cbc2b01a","name":"Bath rugs","section":"Toilet","imgURL":"https://live.staticflickr.com/3831/9697204231_cb30defa44_n.jpg","person":"Undefined","status":""},{"_id":"62622faad4c6e5a0cbc2b01b","name":"Ice mold","section":"Kitchen","imgURL":"https://live.staticflickr.com/4091/5069412100_0f14e8bf9d_n.jpg","person":"Mateus","status":"checked"},{"_id":"62622faad4c6e5a0cbc2b01c","name":"Biscuit jars","section":"Kitchen","imgURL":"https://live.staticflickr.com/7026/6822936795_9770e2d72e_n.jpg","person":"Undefined","status":""},{"_id":"62622faad4c6e5a0cbc2b01d","name":"Coffee powder","section":"Food","imgURL":"https://live.staticflickr.com/8184/8348877158_5831a3dbb8_n.jpg","person":"Undefined","status":""},{"_id":"62622faad4c6e5a0cbc2b01e","name":"Broom","section":"Outside","imgURL":"https://live.staticflickr.com/6/74857035_50281b0e4c_n.jpg","person":"Undefined","status":""},{"_id":"62622faad4c6e5a0cbc2b01f","name":"Dust pan","section":"Outside","imgURL":"https://live.staticflickr.com/7087/7301933946_73d26aed9d_n.jpg","person":"Mateus","status":"checked"},{"_id":"62622faad4c6e5a0cbc2b020","name":"Vegetable brush","section":"Outside","imgURL":"https://live.staticflickr.com/193/503642167_cbb71645db_n.jpg","person":"Mateus","status":"checked"},{"_id":"6262f9c7c0a4701afe024008","name":"Tomatoes","section":"Food","imgURL":"http://live.staticflickr.com/3538/3314009633_56d4f3aff8_n.jpg","person":"Undefined","status":""},{"_id":"62630458c14086a00209c109","name":"Rice","section":"Food","imgURL":"http://live.staticflickr.com/100/254742760_7d8a289448_n.jpg","person":"Undefined","status":""},{"_id":"62638a466044a01be169ec00","name":"Pepper","section":"Food","imgURL":"http://live.staticflickr.com/5715/30347659883_92bf8db4f6_n.jpg","person":"Undefined","status":""},{"_id":"6264353bb1fdc068e61bbe28","name":"Clothespin plastic basket","section":"Outside","imgURL":"https://live.staticflickr.com/5054/5547682904_59eee54009_n.jpg","person":"Mateus","status":"checked"},{"_id":"6264373a6381cbc49dd2f00d","name":"Clothespins","section":"Outside","imgURL":"https://live.staticflickr.com/3556/3475502972_b833df9997_n.jpg","person":"Mateus","status":"checked"},{"_id":"62643f8641925acf79570394","name":"Kitchen squeegee","section":"Kitchen","imgURL":"https://live.staticflickr.com/2850/13670252354_a2d21fcc65_n.jpg","person":"Mateus","status":"checked"},{"_id":"626440a941925acf79570395","name":"Plastic sieve","section":"Kitchen","imgURL":"https://live.staticflickr.com/65535/52018469858_e9a6100536_n.jpg","person":"Mateus","status":"checked"},{"_id":"626441f041925acf79570396","name":"Garbage bags","section":"Outside","imgURL":"https://live.staticflickr.com/65535/51362990130_3b617dc712_n.jpg","person":"Mateus","status":"checked"},{"_id":"6264425f41925acf79570397","name":"Coffee filter holder","section":"Kitchen","imgURL":"https://live.staticflickr.com/3411/3303244693_385560fcf8_n.jpg","person":"Mateus","status":"checked"},{"_id":"626443d341925acf79570398","name":"Manual grater and slicer","section":"Kitchen","imgURL":"https://live.staticflickr.com/4346/36596173386_0e0d3236fe_c.jpg","person":"Mateus","status":"checked"},{"_id":"6264443341925acf79570399","name":"Plastic funnel","section":"Kitchen","imgURL":"https://live.staticflickr.com/6211/6360506353_b025c4291f_b.jpg","person":"Mateus","status":"checked"},{"_id":"626444a741925acf7957039a","name":"Manual garlic crusher","section":"Kitchen","imgURL":"https://live.staticflickr.com/4437/36098551040_820b4a91df_n.jpg","person":"Mateus","status":"checked"},{"_id":"626445e641925acf7957039b","name":"Food plastic bags","section":"Kitchen","imgURL":"https://live.staticflickr.com/3071/2885607736_a49a4ac7b0_n.jpg","person":"Mateus","status":"checked"},{"_id":"6264478141925acf7957039c","name":"Aluminium foil","section":"Kitchen","imgURL":"https://live.staticflickr.com/65535/49857430768_39a1d23008_n.jpg","person":"Mateus","status":"checked"},{"_id":"626447e841925acf7957039d","name":"Plastic wrap","section":"Kitchen","imgURL":"https://live.staticflickr.com/65535/49414186231_00d9e5f4be_n.jpg","person":"Mateus","status":"checked"}]